language_tools/__init__.py
language_tools/tools/__init__.py
language_tools/tools/abstractive_summarization.py
language_tools/tools/conversation_summarization.py
language_tools/tools/conversational_language_understanding.py
language_tools/tools/conversational_pii.py
language_tools/tools/entity_recognition.py
language_tools/tools/extractive_summarization.py
language_tools/tools/key_phrase_extraction.py
language_tools/tools/language_detection.py
language_tools/tools/pii_entity_recognition.py
language_tools/tools/sentiment_analysis.py
language_tools/tools/translator.py
language_tools/tools/utils.py
language_tools/yamls/__init__.py
language_tools/yamls/abstractive_summarization.yaml
language_tools/yamls/conversation_summarization.yaml
language_tools/yamls/conversational_language_understanding.yaml
language_tools/yamls/conversational_pii.yaml
language_tools/yamls/entity_recognition.yaml
language_tools/yamls/extractive_summarization.yaml
language_tools/yamls/key_phrase_extraction.yaml
language_tools/yamls/language_detection.yaml
language_tools/yamls/pii_entity_recognition.yaml
language_tools/yamls/sentiment_analysis.yaml
language_tools/yamls/translator.yaml
language_utils/__init__.py
language_utils/language_client.py
language_utils/language_formatter_utils.py
language_utils/language_mode.py
language_utils/language_parser_utils.py
language_utils/language_skill.py
language_utils/language_tool_utils.py
promptflow_azure_ai_language-0.1.14.dist-info/LICENSE
promptflow_azure_ai_language-0.1.14.dist-info/METADATA
promptflow_azure_ai_language-0.1.14.dist-info/NOTICE.txt
promptflow_azure_ai_language-0.1.14.dist-info/WHEEL
promptflow_azure_ai_language-0.1.14.dist-info/entry_points.txt
promptflow_azure_ai_language-0.1.14.dist-info/top_level.txt
promptflow_azure_ai_language-0.1.14.dist-info/RECORD
