Metadata-Version: 2.1
Name: promptflow-azure-ai-language
Version: 0.1.14
Summary: Collection of Azure AI Language Prompt flow tools.
Home-page: UNKNOWN
Author: Microsoft Corporation
Maintainer-email: taincidents@microsoft.com
License: MIT License
Platform: UNKNOWN
Requires-Python: >=3.9
License-File: LICENSE
License-File: NOTICE.txt
Requires-Dist: requests
Requires-Dist: promptflow>=1.13.0
